LICENSE
README.md
setup.py
GalCraft/MainProcess.py
GalCraft/__init__.py
GalCraft/_version.py
GalCraft.egg-info/PKG-INFO
GalCraft.egg-info/SOURCES.txt
GalCraft.egg-info/dependency_links.txt
GalCraft.egg-info/entry_points.txt
GalCraft.egg-info/not-zip-safe
GalCraft.egg-info/requires.txt
GalCraft.egg-info/top_level.txt
GalCraft/instrument/MUSE-WFM.json
GalCraft/instrument/__init__.py
GalCraft/instrument/a_MUSE-WFM
GalCraft/instrument/lsf_CONROYCAT
GalCraft/instrument/lsf_MUSE-WFM
GalCraft/instrument/lsf_MUSE-WFM-GIST
GalCraft/instrument/lsf_MUSE-alphaMC
GalCraft/instrument/lsf_PEGASEHR
GalCraft/instrument/lsf_alphaMC
GalCraft/instrument/lsf_xshooter
GalCraft/modules/Binner.py
GalCraft/modules/Cot.py
GalCraft/modules/CubeMaker.py
GalCraft/modules/SSPLoader.py
GalCraft/modules/SpecGenerator.py
GalCraft/modules/SpecGeneratorPix.py
GalCraft/modules/__init__.py
GalCraft/modules/constant.py
GalCraft/modules/utils.py
GalCraft/ssp_utils/__init__.py
GalCraft/ssp_utils/alphaMC_util.py
GalCraft/ssp_utils/conroyinmiles_util.py
GalCraft/ssp_utils/miles_util.py
GalCraft/ssp_utils/pegasehr_interp_util.py
GalCraft/ssp_utils/pegasehr_util.py
GalCraft/ssp_utils/xshooter_util.py