Metadata-Version: 2.1
Name: GalCraft
Version: 1.6.0
Summary: GalCraft: Building integral-field spectrograph data cubes of the Galaxy
Home-page: https://github.com/purmortal/galcraft
Author: Zixian Wang (Purmortal)
Author-email: wang.zixian.astro@gmail.com
Classifier: Intended Audience :: Science/Research
Classifier: Topic :: Scientific/Engineering :: Astronomy
Classifier: Programming Language :: Python :: 3
Classifier: License :: OSI Approved :: MIT License
Requires-Python: >=3.6
License-File: LICENSE
Requires-Dist: astropy
Requires-Dist: numpy
Requires-Dist: scipy
Requires-Dist: matplotlib
Requires-Dist: ebfpy
Requires-Dist: ephem
Requires-Dist: spectres
